image_optimizer/__init__.py
image_optimizer/fields.py
image_optimizer/settings.py
image_optimizer/utils.py
django_image_optimizer_way2enjoy-1.0.0.dist-info/LICENSE
django_image_optimizer_way2enjoy-1.0.0.dist-info/METADATA
django_image_optimizer_way2enjoy-1.0.0.dist-info/WHEEL
django_image_optimizer_way2enjoy-1.0.0.dist-info/top_level.txt
django_image_optimizer_way2enjoy-1.0.0.dist-info/RECORD
