Metadata-Version: 2.1
Name: django-image-optimizer-way2enjoy
Version: 1.0.0
Summary: Django Image Optimizer (Compressor)
Home-page: https://github.com/way2enjoy2/django-image-optimizer-way2enjoy
Author: Way2enjoy (James)
Author-email: support@way2enjoy.com
License: MIT
Download-URL: https://github.com/way2enjoy2/django-image-optimizer-way2enjoy/tarball/v1.0.0
Keywords: image optimizer,django image optimizer,image optimizer
Platform: UNKNOWN
Classifier: Development Status :: 5 - Production/Stable
Classifier: Environment :: Web Environment
Classifier: Framework :: Django
Classifier: Framework :: Django :: 1.8
Classifier: Framework :: Django :: 1.9
Classifier: Framework :: Django :: 1.10
Classifier: Framework :: Django :: 1.11
Classifier: Framework :: Django :: 2.0
Classifier: Intended Audience :: Developers
Classifier: Operating System :: OS Independent
Classifier: Programming Language :: Python
Classifier: Programming Language :: Python :: 2.7
Classifier: Programming Language :: Python :: 3.3
Classifier: Programming Language :: Python :: 3.5
Classifier: Topic :: Software Development :: Libraries :: Python Modules
Classifier: License :: OSI Approved :: MIT License
Requires-Dist: Django
Requires-Dist: Pillow
Requires-Dist: requests
Requires-Dist: way2E
